pyvim/__init__.py
pyvim/current.py
pyvim/function.py
pyvim/highlighting.py
pyvim/job.py
pyvim/mapping.py
pyvim/print.py
pyvim/register.py
pyvim/utilities.py
vimlib-0.0.13.dist-info/LICENSE
vimlib-0.0.13.dist-info/METADATA
vimlib-0.0.13.dist-info/WHEEL
vimlib-0.0.13.dist-info/top_level.txt
vimlib-0.0.13.dist-info/RECORD
