Metadata-Version: 2.1
Name: vimlib
Version: 0.0.13
Summary: Friendly Python interface for interacting with Vim.
Home-page: https://github.com/AceofSpades5757/vimlib
Author: Kyle L. Davis
Author-email: AceofSpades5757.github@gmail.com
License: MIT
Project-URL: Documentation, https://vimlib.readthedocs.io/en/latest/
Project-URL: Author, https://github.com/AceofSpades5757
Classifier: Programming Language :: Python :: 3
Classifier: Operating System :: OS Independent
Classifier: Development Status :: 2 - Pre-Alpha
Classifier: License :: OSI Approved :: MIT License
Classifier: Programming Language :: Python :: 3.6
Classifier: Programming Language :: Python :: 3.7
Classifier: Programming Language :: Python :: 3.8
Classifier: Programming Language :: Python :: 3.9
Classifier: Programming Language :: Python :: 3.10
Requires-Python: >=3.6
License-File: LICENSE
